html_loader/__init__.py
html_loader/__main__.py
html_loader-1.0.0.dist-info/LICENSE
html_loader-1.0.0.dist-info/METADATA
html_loader-1.0.0.dist-info/WHEEL
html_loader-1.0.0.dist-info/top_level.txt
html_loader-1.0.0.dist-info/RECORD
