Metadata-Version: 2.1
Name: html-loader
Version: 1.0.0
Summary: HTML to GUI
Home-page: https://wispace.ru/
Author: WiSpace
Author-email: wiforumit@gmail.com
Requires-Python: >=3.6
License-File: LICENSE
